sophosfirewall_python/admin.py
sophosfirewall_python/api_client.py
sophosfirewall_python/authen.py
sophosfirewall_python/backup.py
sophosfirewall_python/firewallapi.py
sophosfirewall_python/firewallrule.py
sophosfirewall_python/firewallrulegroup.py
sophosfirewall_python/host.py
sophosfirewall_python/ips.py
sophosfirewall_python/network.py
sophosfirewall_python/profile.py
sophosfirewall_python/reports.py
sophosfirewall_python/service.py
sophosfirewall_python/system.py
sophosfirewall_python/templates/createadminprofile.j2
sophosfirewall_python/templates/createfqdnhost.j2
sophosfirewall_python/templates/createfqdnhostgroup.j2
sophosfirewall_python/templates/createfwrule.j2
sophosfirewall_python/templates/createfwrulegroup.j2
sophosfirewall_python/templates/createiphost.j2
sophosfirewall_python/templates/createiphostgroup.j2
sophosfirewall_python/templates/createipnetwork.j2
sophosfirewall_python/templates/createiprange.j2
sophosfirewall_python/templates/createservice.j2
sophosfirewall_python/templates/createserviceacl.j2
sophosfirewall_python/templates/createservicegroup.j2
sophosfirewall_python/templates/createurlgroup.j2
sophosfirewall_python/templates/createuser.j2
sophosfirewall_python/templates/createuseractivity.j2
sophosfirewall_python/templates/createwebfilterpolicy.j2
sophosfirewall_python/templates/createzone.j2
sophosfirewall_python/templates/updateadminpassword.j2
sophosfirewall_python/templates/updateadminprofile.j2
sophosfirewall_python/templates/updatebackup.j2
sophosfirewall_python/templates/updatefqdnhostgroup.j2
sophosfirewall_python/templates/updatefwrule.j2
sophosfirewall_python/templates/updatefwrulegroup.j2
sophosfirewall_python/templates/updateiphostgroup.j2
sophosfirewall_python/templates/updateservice.j2
sophosfirewall_python/templates/updateserviceacl.j2
sophosfirewall_python/templates/updateservicegroup.j2
sophosfirewall_python/templates/updateurlgroup.j2
sophosfirewall_python/templates/updateuserpassword.j2
sophosfirewall_python-0.1.66.dist-info/METADATA
sophosfirewall_python-0.1.66.dist-info/WHEEL
sophosfirewall_python-0.1.66.dist-info/licenses/LICENSE
sophosfirewall_python-0.1.66.dist-info/RECORD
