Metadata-Version: 2.4
Name: sophosfirewall-python
Version: 0.1.66
Summary: Python SDK for Sophos Firewall
License-File: LICENSE
Author: Matt Mullen
Author-email: matt.mullen@sophos.com
Requires-Python: >=3.9,<4.0
Classifier: Programming Language :: Python :: 3
Classifier: Programming Language :: Python :: 3.9
Classifier: Programming Language :: Python :: 3.10
Classifier: Programming Language :: Python :: 3.11
Classifier: Programming Language :: Python :: 3.12
Classifier: Programming Language :: Python :: 3.13
Classifier: Programming Language :: Python :: 3.14
Requires-Dist: Jinja2 (>=3.1.2,<4.0.0)
Requires-Dist: requests (>=2.31.0,<3.0.0)
Requires-Dist: xmltodict (>=0.13.0,<0.14.0)
